perfmon/__init__.py
perfmon/p2util.py
perfmon/perfmon.py
perfmon/perfmonKit.py
perfmon-0.0.3.dist-info/LICENSE
perfmon-0.0.3.dist-info/METADATA
perfmon-0.0.3.dist-info/WHEEL
perfmon-0.0.3.dist-info/top_level.txt
perfmon-0.0.3.dist-info/zip-safe
perfmon-0.0.3.dist-info/RECORD
