Metadata-Version: 2.1
Name: perfmon
Version: 0.0.3
Summary: A Python library for test android perf .
Home-page: https://github.com/roberchen820/forgetme
Author: tiantain
Author-email: 858898530@qq.com
License: MIT
Platform: UNKNOWN
Classifier: Environment :: Web Environment
Classifier: Intended Audience :: Developers
Classifier: License :: OSI Approved :: MIT License
Classifier: Topic :: Multimedia :: Video
Classifier: Topic :: Internet
Classifier: Topic :: Software Development :: Libraries :: Python Modules
Classifier: Programming Language :: Python :: 2.7
